setup.cfg
setup.py
dynarray/__init__.py
dynarray/dynamic_array.py
dynarray.egg-info/PKG-INFO
dynarray.egg-info/SOURCES.txt
dynarray.egg-info/dependency_links.txt
dynarray.egg-info/requires.txt
dynarray.egg-info/top_level.txt