Metadata-Version: 1.1
Name: dynarray
Version: 0.1.3
Summary: Dynamically growable numpy arrays.
Home-page: https://github.com/maciejkula/dynarray
Author: Maciej Kula
Author-email: UNKNOWN
License: MIT
Download-URL: https://github.com/maciejkula/dynarray/tarball/0.1.3
Platform: UNKNOWN
Classifier: Development Status :: 3 - Alpha
Classifier: License :: OSI Approved :: MIT License
